{
  "roots": [
    {
      "key": "rkxa6gvow5h134shne4kfpv",
      "title": "Branded",
      "icon": "plusOutlined",
      "hasTitleNumberOutlined": false,
      "vaultName": "weberon-docs",
      "children": [
        {
          "key": "7kvn34av9mw3siymi08qfrd",
          "title": "Showcase",
          "icon": null,
          "hasTitleNumberOutlined": false,
          "vaultName": "weberon-docs",
          "children": []
        }
      ]
    }
  ],
  "child2parent": {
    "rkxa6gvow5h134shne4kfpv": null,
    "7kvn34av9mw3siymi08qfrd": "rkxa6gvow5h134shne4kfpv"
  },
  "notesLabelById": {
    "rkxa6gvow5h134shne4kfpv": "Branded",
    "7kvn34av9mw3siymi08qfrd": "Showcase"
  }
}
